arghonaut/__init__.py
arghonaut/__main__.py
arghonaut/common.py
arghonaut/interface.py
arghonaut/interpreter.py
arghonaut/main.py
arghonaut-1.5.0.dist-info/entry_points.txt
arghonaut-1.5.0.dist-info/LICENSE.txt
arghonaut-1.5.0.dist-info/WHEEL
arghonaut-1.5.0.dist-info/METADATA
arghonaut-1.5.0.dist-info/RECORD
