Metadata-Version: 2.1
Name: arghonaut
Version: 1.5.0
Summary: Interactive Interpreter for Argh!
Author: Aaron Friesen
Classifier: License :: OSI Approved :: GNU General Public License v3 or later (GPLv3+)
Project-URL: Home, https://frie.dev/arghonaut
